[
  {
    "pk": 1,
    "model": "trees.timberprice",
    "fields": {
      "price": 330.0,
      "variant": 29,
      "timber_type": "df_hrv"
    }
  },
  {
    "pk": 2,
    "model": "trees.timberprice",
    "fields": {
      "price": 585.0,
      "variant": 31,
      "timber_type": "df_hrv"
    }
  },
  {
    "pk": 3,
    "model": "trees.timberprice",
    "fields": {
      "price": 378.0,
      "variant": 32,
      "timber_type": "df_hrv"
    }
  },
  {
    "pk": 4,
    "model": "trees.timberprice",
    "fields": {
      "price": 435.0,
      "variant": 33,
      "timber_type": "df_hrv"
    }
  },
  {
    "pk": 5,
    "model": "trees.timberprice",
    "fields": {
      "price": 579.0,
      "variant": 28,
      "timber_type": "df_hrv"
    }
  },
  {
    "pk": 6,
    "model": "trees.timberprice",
    "fields": {
      "price": 579.0,
      "variant": 30,
      "timber_type": "df_hrv"
    }
  },
  {
    "pk": 9,
    "model": "trees.timberprice",
    "fields": {
      "price": 0.0,
      "variant": 31,
      "timber_type": "hw_hrv"
    }
  },
  {
    "pk": 10,
    "model": "trees.timberprice",
    "fields": {
      "price": 0.0,
      "variant": 31,
      "timber_type": "mnconhrv"
    }
  },
  {
    "pk": 11,
    "model": "trees.timberprice",
    "fields": {
      "price": 0.0,
      "variant": 31,
      "timber_type": "mnhw_hrv"
    }
  },
  {
    "pk": 13,
    "model": "trees.timberprice",
    "fields": {
      "price": 0.0,
      "variant": 31,
      "timber_type": "wj_hrv"
    }
  },
  {
    "pk": 15,
    "model": "trees.timberprice",
    "fields": {
      "price": 0.0,
      "variant": 31,
      "timber_type": "sprc_hrv"
    }
  },
  {
    "pk": 16,
    "model": "trees.timberprice",
    "fields": {
      "price": 0.0,
      "variant": 29,
      "timber_type": "cedr_hrv"
    }
  },
  {
    "pk": 18,
    "model": "trees.timberprice",
    "fields": {
      "price": 0.0,
      "variant": 29,
      "timber_type": "hw_hrv"
    }
  },
  {
    "pk": 19,
    "model": "trees.timberprice",
    "fields": {
      "price": 0.0,
      "variant": 29,
      "timber_type": "mnconhrv"
    }
  },
  {
    "pk": 20,
    "model": "trees.timberprice",
    "fields": {
      "price": 0.0,
      "variant": 29,
      "timber_type": "mnhw_hrv"
    }
  },
  {
    "pk": 22,
    "model": "trees.timberprice",
    "fields": {
      "price": 0.0,
      "variant": 29,
      "timber_type": "wj_hrv"
    }
  },
  {
    "pk": 27,
    "model": "trees.timberprice",
    "fields": {
      "price": 0.0,
      "variant": 32,
      "timber_type": "hw_hrv"
    }
  },
  {
    "pk": 29,
    "model": "trees.timberprice",
    "fields": {
      "price": 0.0,
      "variant": 32,
      "timber_type": "mnhw_hrv"
    }
  },
  {
    "pk": 31,
    "model": "trees.timberprice",
    "fields": {
      "price": 0.0,
      "variant": 32,
      "timber_type": "wj_hrv"
    }
  },
  {
    "pk": 36,
    "model": "trees.timberprice",
    "fields": {
      "price": 0.0,
      "variant": 33,
      "timber_type": "hw_hrv"
    }
  },
  {
    "pk": 37,
    "model": "trees.timberprice",
    "fields": {
      "price": 0.0,
      "variant": 33,
      "timber_type": "mnconhrv"
    }
  },
  {
    "pk": 38,
    "model": "trees.timberprice",
    "fields": {
      "price": 0.0,
      "variant": 33,
      "timber_type": "mnhw_hrv"
    }
  },
  {
    "pk": 40,
    "model": "trees.timberprice",
    "fields": {
      "price": 0.0,
      "variant": 33,
      "timber_type": "wj_hrv"
    }
  },
  {
    "pk": 42,
    "model": "trees.timberprice",
    "fields": {
      "price": 0.0,
      "variant": 33,
      "timber_type": "sprc_hrv"
    }
  },
  {
    "pk": 46,
    "model": "trees.timberprice",
    "fields": {
      "price": 0.0,
      "variant": 28,
      "timber_type": "mnconhrv"
    }
  },
  {
    "pk": 48,
    "model": "trees.timberprice",
    "fields": {
      "price": 0.0,
      "variant": 28,
      "timber_type": "pine_hrv"
    }
  },
  {
    "pk": 49,
    "model": "trees.timberprice",
    "fields": {
      "price": 0.0,
      "variant": 28,
      "timber_type": "wj_hrv"
    }
  },
  {
    "pk": 55,
    "model": "trees.timberprice",
    "fields": {
      "price": 0.0,
      "variant": 30,
      "timber_type": "mnconhrv"
    }
  },
  {
    "pk": 57,
    "model": "trees.timberprice",
    "fields": {
      "price": 0.0,
      "variant": 30,
      "timber_type": "pine_hrv"
    }
  },
  {
    "pk": 58,
    "model": "trees.timberprice",
    "fields": {
      "price": 0.0,
      "variant": 30,
      "timber_type": "wj_hrv"
    }
  },
  {
    "pk": 51,
    "model": "trees.timberprice",
    "fields": {
      "price": 415.0,
      "variant": 28,
      "timber_type": "sprc_hrv"
    }
  },
  {
    "pk": 43,
    "model": "trees.timberprice",
    "fields": {
      "price": 955.0,
      "variant": 28,
      "timber_type": "cedr_hrv"
    }
  },
  {
    "pk": 45,
    "model": "trees.timberprice",
    "fields": {
      "price": 590.0,
      "variant": 28,
      "timber_type": "hw_hrv"
    }
  },
  {
    "pk": 47,
    "model": "trees.timberprice",
    "fields": {
      "price": 420.0,
      "variant": 28,
      "timber_type": "mnhw_hrv"
    }
  },
  {
    "pk": 50,
    "model": "trees.timberprice",
    "fields": {
      "price": 490.0,
      "variant": 28,
      "timber_type": "ww_hrv"
    }
  },
  {
    "pk": 21,
    "model": "trees.timberprice",
    "fields": {
      "price": 359.0,
      "variant": 29,
      "timber_type": "pine_hrv"
    }
  },
  {
    "pk": 24,
    "model": "trees.timberprice",
    "fields": {
      "price": 245.0,
      "variant": 29,
      "timber_type": "sprc_hrv"
    }
  },
  {
    "pk": 23,
    "model": "trees.timberprice",
    "fields": {
      "price": 250.0,
      "variant": 29,
      "timber_type": "ww_hrv"
    }
  },
  {
    "pk": 25,
    "model": "trees.timberprice",
    "fields": {
      "price": 830.0,
      "variant": 32,
      "timber_type": "cedr_hrv"
    }
  },
  {
    "pk": 28,
    "model": "trees.timberprice",
    "fields": {
      "price": 351.0,
      "variant": 32,
      "timber_type": "mnconhrv"
    }
  },
  {
    "pk": 30,
    "model": "trees.timberprice",
    "fields": {
      "price": 369.0,
      "variant": 32,
      "timber_type": "pine_hrv"
    }
  },
  {
    "pk": 33,
    "model": "trees.timberprice",
    "fields": {
      "price": 336.0,
      "variant": 32,
      "timber_type": "sprc_hrv"
    }
  },
  {
    "pk": 32,
    "model": "trees.timberprice",
    "fields": {
      "price": 347.0,
      "variant": 32,
      "timber_type": "ww_hrv"
    }
  },
  {
    "pk": 7,
    "model": "trees.timberprice",
    "fields": {
      "price": 600.0,
      "variant": 31,
      "timber_type": "cedr_hrv"
    }
  },
  {
    "pk": 12,
    "model": "trees.timberprice",
    "fields": {
      "price": 420.0,
      "variant": 31,
      "timber_type": "pine_hrv"
    }
  },
  {
    "pk": 14,
    "model": "trees.timberprice",
    "fields": {
      "price": 500.0,
      "variant": 31,
      "timber_type": "ww_hrv"
    }
  },
  {
    "pk": 34,
    "model": "trees.timberprice",
    "fields": {
      "price": 600.0,
      "variant": 33,
      "timber_type": "cedr_hrv"
    }
  },
  {
    "pk": 39,
    "model": "trees.timberprice",
    "fields": {
      "price": 300.0,
      "variant": 33,
      "timber_type": "pine_hrv"
    }
  },
  {
    "pk": 41,
    "model": "trees.timberprice",
    "fields": {
      "price": 400.0,
      "variant": 33,
      "timber_type": "ww_hrv"
    }
  },
  {
    "pk": 52,
    "model": "trees.timberprice",
    "fields": {
      "price": 955.0,
      "variant": 30,
      "timber_type": "cedr_hrv"
    }
  },
  {
    "pk": 54,
    "model": "trees.timberprice",
    "fields": {
      "price": 590.0,
      "variant": 30,
      "timber_type": "hw_hrv"
    }
  },
  {
    "pk": 56,
    "model": "trees.timberprice",
    "fields": {
      "price": 420.0,
      "variant": 30,
      "timber_type": "mnhw_hrv"
    }
  },
  {
    "pk": 60,
    "model": "trees.timberprice",
    "fields": {
      "price": 415.0,
      "variant": 30,
      "timber_type": "sprc_hrv"
    }
  },
  {
    "pk": 59,
    "model": "trees.timberprice",
    "fields": {
      "price": 490.0,
      "variant": 30,
      "timber_type": "ww_hrv"
    }
  }
]